mhi/psout/CurveFile.dll
mhi/psout/__init__.py
mhi/psout/__main__.py
mhi/psout/_psout.cp39-win_amd64.pyd
mhi/psout/mhi-psout.chm
mhi/psout/py.typed
mhi_psout-1.0.5.dist-info/LICENSE
mhi_psout-1.0.5.dist-info/METADATA
mhi_psout-1.0.5.dist-info/WHEEL
mhi_psout-1.0.5.dist-info/top_level.txt
mhi_psout-1.0.5.dist-info/RECORD
