Metadata-Version: 2.1
Name: mhi-psout
Version: 1.0.5
Summary: Manitoba Hydro International: PSOUT File Reader
Home-page: https://www.pscad.com/webhelp-v5-al/index.html
Author: Manitoba Hydro International Ltd.
Author-email: pscad@mhi.ca
License: BSD-3-Clause-Clear
Classifier: Development Status :: 5 - Production/Stable
Classifier: Programming Language :: Python :: 3
Classifier: Programming Language :: Python :: 3.6
Classifier: Programming Language :: Python :: 3.7
Classifier: Programming Language :: Python :: 3.8
Classifier: Programming Language :: Python :: 3.9
Classifier: Programming Language :: Python :: 3.10
Classifier: Programming Language :: Python :: 3.11
Classifier: Programming Language :: Python :: 3.12
Classifier: Programming Language :: Python :: 3.13
Classifier: License :: OSI Approved :: BSD License
Classifier: Operating System :: Microsoft :: Windows
Requires: wheel
Requires-Python: >=3.6
License-File: LICENSE
